{
    "CarBrainPPO": {
        "checkpoints": [
            {
                "steps": 5913,
                "file_path": "results\\1\\CarBrainPPO\\CarBrainPPO-5913.onnx",
                "reward": 56.126214583714805,
                "creation_time": 1628674112.956633
            }
        ],
        "final_checkpoint": {
            "steps": 5913,
            "file_path": "results\\1\\CarBrainPPO.onnx",
            "reward": 56.126214583714805,
            "creation_time": 1628674112.956633
        }
    },
    "metadata": {
        "stats_format_version": "0.2.0",
        "mlagents_version": "0.25.0",
        "torch_version": "1.7.1+cu110"
    }
}