{
    "CarBrain": {
        "checkpoints": [
            {
                "steps": 16156,
                "file_path": "results\\665\\CarBrain\\CarBrain-16156.onnx",
                "reward": 63.715817609911454,
                "creation_time": 1627480223.575518
            }
        ],
        "final_checkpoint": {
            "steps": 16156,
            "file_path": "results\\665\\CarBrain.onnx",
            "reward": 63.715817609911454,
            "creation_time": 1627480223.575518
        }
    },
    "metadata": {
        "stats_format_version": "0.2.0",
        "mlagents_version": "0.25.0",
        "torch_version": "1.7.1+cu110"
    }
}